{
  "_format": "hh-sol-cache-2",
  "files": {
    "/home/raymondintell/Desktop/deployClassWork/Greeter2/contracts/Greeter.sol": {
      "lastModificationDate": 1770823927408,
      "contentHash": "61204bdc001359e3fbd60ff11c68d6e3",
      "sourceName": "contracts/Greeter.sol",
      "solcConfig": {
        "version": "0.8.30",
        "settings": {
          "evmVersion": "paris",
          "optimizer": {
            "enabled": false,
            "runs": 200
          },
          "outputSelection": {
            "*": {
              "*": [
                "abi",
                "evm.bytecode",
                "evm.deployedBytecode",
                "evm.methodIdentifiers",
                "metadata"
              ],
              "": [
                "ast"
              ]
            }
          }
        }
      },
      "imports": [],
      "versionPragmas": [
        "0.8.30"
      ],
      "artifacts": [
        "Greeter"
      ]
    }
  }
}
